packages/__init__.py
packages/api/__init__.py
packages/api/main.py
packages/cli/__init__.py
packages/cli/commands/hello.py
packages/cli/main.py
packages/cli/main_simple.py
packages/core/README.md
packages/core/__init__.py
packages/core/base/__init__.py
packages/core/base/edi_ast.py
packages/core/base/enhanced_parser.py
packages/core/base/parser.py
packages/core/base/validation.py
packages/core/emitter.py
packages/core/errors/__init__.py
packages/core/errors/context.py
packages/core/errors/exceptions.py
packages/core/errors/handler.py
packages/core/interfaces/__init__.py
packages/core/interfaces/parser_interface.py
packages/core/parser.py
packages/core/plugins/__init__.py
packages/core/plugins/api.py
packages/core/plugins/base_plugin.py
packages/core/plugins/factory.py
packages/core/plugins/implementations/__init__.py
packages/core/plugins/implementations/plugin_270_271.py
packages/core/plugins/implementations/plugin_276_277.py
packages/core/plugins/implementations/plugin_835.py
packages/core/plugins/implementations/plugin_837p.py
packages/core/schema.py
packages/core/schemas/x12/270.json
packages/core/schemas/x12/271.json
packages/core/schemas/x12/276.json
packages/core/schemas/x12/277.json
packages/core/schemas/x12/835.json
packages/core/schemas/x12/837.json
packages/core/transactions/__init__.py
packages/core/transactions/t270/__init__.py
packages/core/transactions/t270/ast.py
packages/core/transactions/t270/parser.py
packages/core/transactions/t276/__init__.py
packages/core/transactions/t276/ast.py
packages/core/transactions/t276/parser.py
packages/core/transactions/t835/__init__.py
packages/core/transactions/t835/ast.py
packages/core/transactions/t835/parser.py
packages/core/transactions/t835/validators.py
packages/core/transactions/t837p/__init__.py
packages/core/transactions/t837p/ast.py
packages/core/transactions/t837p/parser.py
packages/core/utils/__init__.py
packages/core/utils/formatters.py
packages/core/utils/helpers.py
packages/core/utils/validators.py
edi_cli-0.2.2.dist-info/LICENSE
edi_cli-0.2.2.dist-info/METADATA
edi_cli-0.2.2.dist-info/WHEEL
edi_cli-0.2.2.dist-info/entry_points.txt
edi_cli-0.2.2.dist-info/RECORD
